fasttext_pybind.cpython-312-arm-linux-gnueabihf.so
fasttext/FastText.py
fasttext/__init__.py
fasttext/tests/__init__.py
fasttext/tests/test_configurations.py
fasttext/tests/test_script.py
fasttext/util/__init__.py
fasttext/util/util.py
fasttext_numpy2_wheel-0.9.2.dist-info/LICENSE
fasttext_numpy2_wheel-0.9.2.dist-info/METADATA
fasttext_numpy2_wheel-0.9.2.dist-info/WHEEL
fasttext_numpy2_wheel-0.9.2.dist-info/top_level.txt
fasttext_numpy2_wheel-0.9.2.dist-info/RECORD
